{"commits":[{"id": "38f8a96", "author": "Edward Gorman", "date": "2021-10-10", "message": "Fix file system generation"}, {"id": "e096d2a", "author": "Edward Gorman", "date": "2021-10-09", "message": "Clean up terminal, add errors script"}, {"id": "8af62d6", "author": "Edward Gorman", "date": "2021-10-09", "message": "Update installation and usage instructions"}, {"id": "d2c067b", "author": "Edward Gorman", "date": "2021-10-09", "message": "Add help command, modularlise terminal"}, {"id": "51ea0ca", "author": "Edward Gorman", "date": "2021-10-09", "message": "Add usr folder"}]}
