{"commits":[{"id": "53f93ff", "author": "github-actions", "date": "2022-02-06", "message": "Automatic update (via workflow)"}, {"id": "2acb3c6", "author": "Edward Gorman", "date": "2022-02-06", "message": "Merge pull request #156 from edgorman/151-add-search-to-get"}, {"id": "6cc2500", "author": "Edward Gorman", "date": "2022-02-06", "message": "#151: Add dir search params to get"}, {"id": "a73d6ba", "author": "github-actions", "date": "2022-02-06", "message": "Automatic update (via workflow)"}, {"id": "f72fe2a", "author": "Edward Gorman", "date": "2022-02-06", "message": "Merge pull request #155 from edgorman/154-make-side-panels-collapsible"}]}
